jvc_proxy/__init__.py
jvc_proxy/jvc_proxy.py
jvc_proxy-0.0.1.dist-info/DESCRIPTION.rst
jvc_proxy-0.0.1.dist-info/METADATA
jvc_proxy-0.0.1.dist-info/RECORD
jvc_proxy-0.0.1.dist-info/WHEEL
jvc_proxy-0.0.1.dist-info/entry_points.txt
jvc_proxy-0.0.1.dist-info/metadata.json
jvc_proxy-0.0.1.dist-info/top_level.txt
jvc_proxy-0.0.1.dist-info/zip-safe
