Metadata-Version: 2.0
Name: jvc-proxy
Version: 0.0.1
Summary: Simple Python server to proxy commands to a JVC projector.
Home-page: https://github.com/dermotduffy/jvc_proxy
Author: Dermot Duffy
Author-email: dermot.duffy@gmail.com
License: Apache Software License
Keywords: jvc proxy projector
Platform: any
Classifier: Intended Audience :: Developers
Classifier: License :: OSI Approved :: Apache Software License
Classifier: Operating System :: OS Independent
Classifier: Programming Language :: Python
Classifier: Programming Language :: Python :: 2
Classifier: Programming Language :: Python :: 3
Classifier: Topic :: Home Automation
Requires-Dist: future
